grreader/__init__.py
grreader/gr.py
grreader-0.1.1.dist-info/WHEEL
grreader-0.1.1.dist-info/METADATA
grreader-0.1.1.dist-info/RECORD
